seafileapi/__init__.py
seafileapi/admin.py
seafileapi/client.py
seafileapi/exceptions.py
seafileapi/files.py
seafileapi/group.py
seafileapi/repo.py
seafileapi/repos.py
seafileapi/utils.py
tests/__init__.py
tests/conftest.py
tests/fixtures.py
tests/test_files.py
tests/test_repos.py
tests/utils.py
seafile_api-0.1.2.dist-info/LICENSE
seafile_api-0.1.2.dist-info/METADATA
seafile_api-0.1.2.dist-info/WHEEL
seafile_api-0.1.2.dist-info/top_level.txt
seafile_api-0.1.2.dist-info/RECORD
