Metadata-Version: 2.1
Name: seafile-api
Version: 0.1.2
Summary: Client interface for Seafile Web API (fixed for python3 by https://github.com/cmdkid)
Home-page: http://seafile.com
Author: Shuai Lin
Author-email: linshuai2012@gmail.com
License: BSD
Platform: Any
Classifier: Development Status :: 4 - Beta
Classifier: License :: OSI Approved :: BSD License
Classifier: Operating System :: OS Independent
Classifier: Programming Language :: Python
Requires-Dist: requests
